experiment_goodies/__init__.py
experiment_goodies/geo/__init__.py
experiment_goodies/geo/raster.py
experiment_goodies/geo/vector.py
experiment_goodies/logger/__init__.py
experiment_goodies/logger/experiment_logger.py
experiment_goodies/logger/rainbow_logger.py
experiment_goodies-0.2.7.dist-info/METADATA
experiment_goodies-0.2.7.dist-info/WHEEL
experiment_goodies-0.2.7.dist-info/RECORD
