Metadata-Version: 2.1
Name: experiment-goodies
Version: 0.2.7
Summary: Useful helpers, callbacks and more for experimenting with ml models
Author: Javier Smith
Author-email: javier.smith.dlc@gmail.com
Requires-Python: >=3.10,<4.0
Classifier: Programming Language :: Python :: 3
Classifier: Programming Language :: Python :: 3.10
Classifier: Programming Language :: Python :: 3.11
Classifier: Programming Language :: Python :: 3.12
Provides-Extra: geo
Requires-Dist: geopandas (>=0.14.3,<0.15.0) ; extra == "geo"
Requires-Dist: logutils (>=0.3.5,<0.4.0)
Requires-Dist: matplotlib (>=3.8.2,<4.0.0)
Requires-Dist: mlflow (>=2.10.0,<3.0.0)
Requires-Dist: pydantic (>=2.0,<3.0)
Requires-Dist: python-dotenv (>=1.0.1,<2.0.0)
Requires-Dist: rasterio (>=1.3.9,<2.0.0) ; extra == "geo"
Requires-Dist: rio-cogeo (>=5.2.0,<6.0.0) ; extra == "geo"
